lsrestclient/__init__.py
lsrestclient/auth.py
lsrestclient/client.py
lsrestclient/fixtures.py
lsrestclient/lsfastapi.py
lsrestclient/mock.py
lsrestclient/response.py
lsrestclient/settings.py
lsrestclient/contexts/__init__.py
lsrestclient/contexts/bearer_token.py
lsrestclient/exceptions/ConnectionError.py
lsrestclient/exceptions/DownStreamError.py
lsrestclient/exceptions/__init__.py
lsrestclient/exceptions/raise_errors.py
lsrestclient-3.4.1.dist-info/METADATA
lsrestclient-3.4.1.dist-info/WHEEL
lsrestclient-3.4.1.dist-info/entry_points.txt
lsrestclient-3.4.1.dist-info/RECORD
