Metadata-Version: 2.4
Name: lsrestclient
Version: 3.4.1
Summary: REST Api Client
Author-email: mba <bartel@electronic-shop.lu>
Requires-Python: >=3.13
Requires-Dist: lsjsonclasses<3.0.0,>=2.0.1
Requires-Dist: pydantic-settings<3.0.0,>=2.10.1
Requires-Dist: pydantic<3.0.0,>=2.11.7
Requires-Dist: pydash>4.0.0
Requires-Dist: redis<7.0.0,>=6.4.0
Requires-Dist: requests-cache<2.0.0,>=1.2.1
Requires-Dist: requests<3.0.0,>=2.31.0
Requires-Dist: webexception<2.0.0,>=1.0.5
Provides-Extra: redis
Requires-Dist: redis; extra == 'redis'
